{
  "refreshed_at": "2026-05-16T11:35:28.304573-05:00",
  "refreshed_label": "11:35 AM",
  "tz_label": "Chicago",
  "events": [],
  "focus_html": "",
  "schedule_html": "<p class=\"empty\">Nothing on the calendar.</p>",
  "openwork_html": "\n            <div class=\"task-row\">\n                <span class=\"capsule capsule--tinted\">Mark&#x27;s list</span>\n                <span class=\"task-title\">Send Jeff and Suhas the updated TD stuff</span>\n                <span class=\"capsule capsule--decision\">Overdue &middot; May 11</span>\n            </div>"
}