{
  "refreshed_at": "2026-05-19T17:54:02.939861-05:00",
  "refreshed_label": "5:54 PM",
  "tz_label": "Chicago",
  "events": [
    {
      "id": "modpmtfqqhnq0iu6o03o4trh14",
      "start_iso": "2026-05-19T08:30:00-05:00",
      "end_iso": "2026-05-19T08:55:00-05:00",
      "start_label": "8:30 AM",
      "end_label": "8:55 AM",
      "summary": "IP Performance Reports - Solution Approach",
      "location": "",
      "prep": null
    },
    {
      "id": "hpl33m3kdi2vt7vlrgh5j2hhd4",
      "start_iso": "2026-05-19T09:00:00-05:00",
      "end_iso": "2026-05-19T10:00:00-05:00",
      "start_label": "9:00 AM",
      "end_label": "10:00 AM",
      "summary": "Architecture Huddle (series ends 12/29/26)",
      "location": "EXEC SAT HO (BO3W.B322)",
      "prep": null
    },
    {
      "id": "dln38nikceaig7v2i4vbq9i350",
      "start_iso": "2026-05-19T10:00:00-05:00",
      "end_iso": "2026-05-19T11:00:00-05:00",
      "start_label": "10:00 AM",
      "end_label": "11:00 AM",
      "summary": "Architecture Sync with Kathleen Ores Walsh",
      "location": "",
      "prep": {
        "summary": "No past meeting summaries with Kathleen Ores Walsh exist in your notes \u2014 the prior context available covers SMS architecture, business architecture maturation, and the Architecture of Architecture business case with other stakeholders (Matt, Jonathan, Brian). The prep instructions ask you to review sent emails and come ready to speak to the future of underwriting and an AI use case for underwriting \u2014 neither topic surfaces in your saved notes, so your prep hinges entirely on that email review. Treat this as a fresh context-build with Kathleen until prior meeting notes are captured.",
        "tasks": [
          "Review your sent email history with Kathleen Ores Walsh and extract any threads touching underwriting strategy, AI, or architecture decisions before the meeting.",
          "Formulate a clear point of view on the future of underwriting \u2014 identify whether the strategic direction leans toward automation, risk model modernization, data centralization, or some combination.",
          "Define the specific AI use case for underwriting you plan to present \u2014 name the capability, the business problem it solves, and how it connects to one or more of the five core biometrics (retention, cost to serve, etc.) your architecture practice already anchors to.",
          "Determine what \u2014 if anything \u2014 from the Unified Enterprise Messaging Fabric or Architecture of Architecture work is relevant to an underwriting AI use case, in case Kathleen draws a cross-domain line.",
          "Decide what you need from Kathleen out of this sync \u2014 a decision, an alignment, a resource commitment \u2014 so you can drive to a concrete next step rather than leaving with an open thread."
        ],
        "title": "Architecture Sync with Kathleen Ores Walsh",
        "start_label": "10:00 AM",
        "end_label": "11:00 AM"
      }
    },
    {
      "id": "neo1tsbhd6a4oke2sq0f50ep8c",
      "start_iso": "2026-05-19T11:00:00-05:00",
      "end_iso": "2026-05-19T11:25:00-05:00",
      "start_label": "11:00 AM",
      "end_label": "11:25 AM",
      "summary": "Bi-weekly 1:1 w/Praveena | Mark (series ends 1/4/27)",
      "location": "",
      "prep": {
        "summary": "You and Praveena are mid-stream on a major operational model effort \u2014 specifically the products and services catalog, where Praveena completed pre-work as of 5/6 and was awaiting SME feedback to finalize content. Running threads include the executive workshop narrative around architecture value, the AI requirements automation tool needing industrialization, and organizational anxiety around leadership transitions (Boucher out, Deepak and Dan in). Today's prep instructions point to two things: horizontal planning needs and a review of product/service feedback \u2014 both map directly to the catalog work and the Phase 2 effectiveness deep-dives Praveena has been driving.",
        "tasks": [
          "Review the current state of the products and services catalog \u2014 confirm whether SME feedback has been collected and what gaps remain before the content can be finalized.",
          "Identify what 'horizontal planning' requires from Praveena's workstream \u2014 determine which services, domains, or deliverables need cross-team visibility or coordination inputs.",
          "Pull together any feedback received on architecture products and services since 5/6 \u2014 surface patterns Deepak or other leaders have flagged as missing or underdeveloped.",
          "Check the status of the domain portfolio spreadsheet last reviewed 4/27 \u2014 confirm whether the proposed dotted-box domains (DNS/MVO and Transformation/TVO) have been validated or remain theoretical.",
          "Be ready to discuss how the AI requirements automation prototype fits into the formal catalog \u2014 decide whether it surfaces as a new service entry and how to route it through Chuck without creating friction."
        ],
        "title": "Bi-weekly 1:1 w/Praveena | Mark (series ends 1/4/27)",
        "start_label": "11:00 AM",
        "end_label": "11:25 AM"
      }
    },
    {
      "id": "m8305lvp4o7n0tgppviodv4cro",
      "start_iso": "2026-05-19T11:30:00-05:00",
      "end_iso": "2026-05-19T13:00:00-05:00",
      "start_label": "11:30 AM",
      "end_label": "1:00 PM",
      "summary": "Lunch / Desk Time",
      "location": "",
      "prep": null
    },
    {
      "id": "189t6i7e4dt259rbnitbcqgeeg",
      "start_iso": "2026-05-19T13:00:00-05:00",
      "end_iso": "2026-05-19T13:50:00-05:00",
      "start_label": "1:00 PM",
      "end_label": "1:50 PM",
      "summary": "P&C Change Review Group (CRG)",
      "location": "",
      "prep": null
    },
    {
      "id": "lhom3gjl145u9kveodfes80oi8",
      "start_iso": "2026-05-19T13:30:00-05:00",
      "end_iso": "2026-05-19T14:00:00-05:00",
      "start_label": "1:30 PM",
      "end_label": "2:00 PM",
      "summary": "Weekly: Horizontal Platform WG",
      "location": "",
      "prep": null
    },
    {
      "id": "5f2l7j4a5ji8bvvikgbjh3ou68",
      "start_iso": "2026-05-19T14:00:00-05:00",
      "end_iso": "2026-05-19T15:00:00-05:00",
      "start_label": "2:00 PM",
      "end_label": "3:00 PM",
      "summary": "Monthly: AEF Forum Meeting (2026 series)",
      "location": "",
      "prep": null
    },
    {
      "id": "6o6bmih6b4hpf71a6suj6blcmk",
      "start_iso": "2026-05-19T15:05:00-05:00",
      "end_iso": "2026-05-19T15:55:00-05:00",
      "start_label": "3:05 PM",
      "end_label": "3:55 PM",
      "summary": "Enterprise Architecture Leadership Sync (series ends 1...)",
      "location": "",
      "prep": null
    },
    {
      "id": "nvlg5vai20vaer7h9iipisas80",
      "start_iso": "2026-05-19T18:00:00-05:00",
      "end_iso": "2026-05-19T20:00:00-05:00",
      "start_label": "6:00 PM",
      "end_label": "8:00 PM",
      "summary": "EA Leaders Dinner at Pappasito's Cantina",
      "location": "10501 I-10, San Antonio, TX",
      "prep": null
    }
  ],
  "focus_html": "\n        <section class=\"focus-card\">\n            <div class=\"eyebrow\">Focus &middot; Next up</div>\n            <div class=\"focus-time\">6:00 PM &mdash; 8:00 PM</div>\n            <h2 class=\"focus-title\">EA Leaders Dinner at Pappasito&#x27;s Cantina</h2>\n            <div class=\"focus-loc\">10501 I-10, San Antonio, TX</div>\n            \n        </section>",
  "schedule_html": "\n            <div class=\"t-row\">\n                <div class=\"t-time\">\n                    <div class=\"t-start\">8:30 AM</div>\n                    <div class=\"t-end\">&mdash; 8:55 AM</div>\n                </div>\n                <div class=\"t-rail\"><span></span></div>\n                <div class=\"t-body\">\n                    <div class=\"t-title\">IP Performance Reports - Solution Approach</div>\n                    \n                </div>\n            </div>\n            <div class=\"t-row\">\n                <div class=\"t-time\">\n                    <div class=\"t-start\">9:00 AM</div>\n                    <div class=\"t-end\">&mdash; 10:00 AM</div>\n                </div>\n                <div class=\"t-rail\"><span></span></div>\n                <div class=\"t-body\">\n                    <div class=\"t-title\">Architecture Huddle (series ends 12/29/26)</div>\n                    <div class=\"t-loc\">EXEC SAT HO (BO3W.B322)</div>\n                </div>\n            </div>\n            <div class=\"t-row\">\n                <div class=\"t-time\">\n                    <div class=\"t-start\">10:00 AM</div>\n                    <div class=\"t-end\">&mdash; 11:00 AM</div>\n                </div>\n                <div class=\"t-rail\"><span></span></div>\n                <div class=\"t-body\">\n                    <div class=\"t-title\">Architecture Sync with Kathleen Ores Walsh</div>\n                    \n                </div>\n            </div>\n            <div class=\"t-row\">\n                <div class=\"t-time\">\n                    <div class=\"t-start\">11:00 AM</div>\n                    <div class=\"t-end\">&mdash; 11:25 AM</div>\n                </div>\n                <div class=\"t-rail\"><span></span></div>\n                <div class=\"t-body\">\n                    <div class=\"t-title\">Bi-weekly 1:1 w/Praveena | Mark (series ends 1/4/27)</div>\n                    \n                </div>\n            </div>\n            <div class=\"t-row\">\n                <div class=\"t-time\">\n                    <div class=\"t-start\">11:30 AM</div>\n                    <div class=\"t-end\">&mdash; 1:00 PM</div>\n                </div>\n                <div class=\"t-rail\"><span></span></div>\n                <div class=\"t-body\">\n                    <div class=\"t-title\">Lunch / Desk Time</div>\n                    \n                </div>\n            </div>\n            <div class=\"t-row\">\n                <div class=\"t-time\">\n                    <div class=\"t-start\">1:00 PM</div>\n                    <div class=\"t-end\">&mdash; 1:50 PM</div>\n                </div>\n                <div class=\"t-rail\"><span></span></div>\n                <div class=\"t-body\">\n                    <div class=\"t-title\">P&amp;C Change Review Group (CRG)</div>\n                    \n                </div>\n            </div>\n            <div class=\"t-row\">\n                <div class=\"t-time\">\n                    <div class=\"t-start\">1:30 PM</div>\n                    <div class=\"t-end\">&mdash; 2:00 PM</div>\n                </div>\n                <div class=\"t-rail\"><span></span></div>\n                <div class=\"t-body\">\n                    <div class=\"t-title\">Weekly: Horizontal Platform WG</div>\n                    \n                </div>\n            </div>\n            <div class=\"t-row\">\n                <div class=\"t-time\">\n                    <div class=\"t-start\">2:00 PM</div>\n                    <div class=\"t-end\">&mdash; 3:00 PM</div>\n                </div>\n                <div class=\"t-rail\"><span></span></div>\n                <div class=\"t-body\">\n                    <div class=\"t-title\">Monthly: AEF Forum Meeting (2026 series)</div>\n                    \n                </div>\n            </div>\n            <div class=\"t-row\">\n                <div class=\"t-time\">\n                    <div class=\"t-start\">3:05 PM</div>\n                    <div class=\"t-end\">&mdash; 3:55 PM</div>\n                </div>\n                <div class=\"t-rail\"><span></span></div>\n                <div class=\"t-body\">\n                    <div class=\"t-title\">Enterprise Architecture Leadership Sync (series ends 1...)</div>\n                    \n                </div>\n            </div>\n            <div class=\"t-row\">\n                <div class=\"t-time\">\n                    <div class=\"t-start\">6:00 PM</div>\n                    <div class=\"t-end\">&mdash; 8:00 PM</div>\n                </div>\n                <div class=\"t-rail\"><span></span></div>\n                <div class=\"t-body\">\n                    <div class=\"t-title\">EA Leaders Dinner at Pappasito&#x27;s Cantina</div>\n                    <div class=\"t-loc\">10501 I-10, San Antonio, TX</div>\n                </div>\n            </div>",
  "openwork_html": "\n            <div class=\"task-row\">\n                <span class=\"capsule capsule--tinted\">Mark&#x27;s list</span>\n                <span class=\"task-title\">Consolidate dashboard feedback and custom views for Matt McCoy</span>\n                <span class=\"capsule capsule--caution\">Due May 21</span>\n            </div>\n            <div class=\"task-row\">\n                <span class=\"capsule capsule--tinted\">Mark&#x27;s list</span>\n                <span class=\"task-title\">Prepare offsite feedback cascade for staff and directors</span>\n                <span class=\"capsule capsule--caution\">Due May 20</span>\n            </div>\n            <div class=\"task-row\">\n                <span class=\"capsule capsule--tinted\">Mark&#x27;s list</span>\n                <span class=\"task-title\">Review Horizontal Planning Sheet</span>\n                <span class=\"capsule capsule--caution\">Due May 20</span>\n            </div>",
  "preps": {
    "dln38nikceaig7v2i4vbq9i350": {
      "summary": "No past meeting summaries with Kathleen Ores Walsh exist in your notes \u2014 the prior context available covers SMS architecture, business architecture maturation, and the Architecture of Architecture business case with other stakeholders (Matt, Jonathan, Brian). The prep instructions ask you to review sent emails and come ready to speak to the future of underwriting and an AI use case for underwriting \u2014 neither topic surfaces in your saved notes, so your prep hinges entirely on that email review. Treat this as a fresh context-build with Kathleen until prior meeting notes are captured.",
      "tasks": [
        "Review your sent email history with Kathleen Ores Walsh and extract any threads touching underwriting strategy, AI, or architecture decisions before the meeting.",
        "Formulate a clear point of view on the future of underwriting \u2014 identify whether the strategic direction leans toward automation, risk model modernization, data centralization, or some combination.",
        "Define the specific AI use case for underwriting you plan to present \u2014 name the capability, the business problem it solves, and how it connects to one or more of the five core biometrics (retention, cost to serve, etc.) your architecture practice already anchors to.",
        "Determine what \u2014 if anything \u2014 from the Unified Enterprise Messaging Fabric or Architecture of Architecture work is relevant to an underwriting AI use case, in case Kathleen draws a cross-domain line.",
        "Decide what you need from Kathleen out of this sync \u2014 a decision, an alignment, a resource commitment \u2014 so you can drive to a concrete next step rather than leaving with an open thread."
      ],
      "title": "Architecture Sync with Kathleen Ores Walsh",
      "start_label": "10:00 AM",
      "end_label": "11:00 AM"
    },
    "neo1tsbhd6a4oke2sq0f50ep8c": {
      "summary": "You and Praveena are mid-stream on a major operational model effort \u2014 specifically the products and services catalog, where Praveena completed pre-work as of 5/6 and was awaiting SME feedback to finalize content. Running threads include the executive workshop narrative around architecture value, the AI requirements automation tool needing industrialization, and organizational anxiety around leadership transitions (Boucher out, Deepak and Dan in). Today's prep instructions point to two things: horizontal planning needs and a review of product/service feedback \u2014 both map directly to the catalog work and the Phase 2 effectiveness deep-dives Praveena has been driving.",
      "tasks": [
        "Review the current state of the products and services catalog \u2014 confirm whether SME feedback has been collected and what gaps remain before the content can be finalized.",
        "Identify what 'horizontal planning' requires from Praveena's workstream \u2014 determine which services, domains, or deliverables need cross-team visibility or coordination inputs.",
        "Pull together any feedback received on architecture products and services since 5/6 \u2014 surface patterns Deepak or other leaders have flagged as missing or underdeveloped.",
        "Check the status of the domain portfolio spreadsheet last reviewed 4/27 \u2014 confirm whether the proposed dotted-box domains (DNS/MVO and Transformation/TVO) have been validated or remain theoretical.",
        "Be ready to discuss how the AI requirements automation prototype fits into the formal catalog \u2014 decide whether it surfaces as a new service entry and how to route it through Chuck without creating friction."
      ],
      "title": "Bi-weekly 1:1 w/Praveena | Mark (series ends 1/4/27)",
      "start_label": "11:00 AM",
      "end_label": "11:25 AM"
    }
  }
}